persian_gender_detection/__init__.py
persian_gender_detection/persian_gender_detection.py
persian_gender_detection/gender/iranianNamesDataset.csv
persian_gender_detection/gender/iranian_names_dataset.py
persian_gender_detection-1.4.0.data/data/iranianNamesDataset.csv
persian_gender_detection-1.4.0.data/data/iranian_names_dataset.py
persian_gender_detection-1.4.0.dist-info/LICENSE
persian_gender_detection-1.4.0.dist-info/METADATA
persian_gender_detection-1.4.0.dist-info/WHEEL
persian_gender_detection-1.4.0.dist-info/top_level.txt
persian_gender_detection-1.4.0.dist-info/RECORD
