Metadata-Version: 2.1
Name: persian-gender-detection
Version: 1.4.0
Summary: A simple python package to detect gender by Persian first name. (With more than 19K names).
Home-page: https://github.com/zeoses/persian-gender-detection
Author: Mehraban
License: MIT License
Project-URL: Source, https://github.com/zeoses/persian-gender-detection
Project-URL: Documentation, https://github.com/zeoses/persian-gender-detection
Keywords: persian-gender-detection,farsi gender,iranian gender,name gender,persian gender detection,gender detection
Classifier: License :: OSI Approved :: MIT License
Classifier: Natural Language :: Persian
Classifier: Natural Language :: English
Classifier: Programming Language :: Python :: 3.8
Classifier: Programming Language :: Python :: 3.9
Classifier: Programming Language :: Python :: 3.10
Classifier: Programming Language :: Python :: 3.11
Classifier: Topic :: Software Development :: Libraries
Classifier: Topic :: Software Development :: Libraries :: Python Modules
Classifier: Topic :: Software Development :: Localization
License-File: LICENSE
